CHANGES
LICENSE
MANIFEST.in
README.md
requirements.txt
setup.py
dopysl/__init__.py
dopysl.egg-info/PKG-INFO
dopysl.egg-info/SOURCES.txt
dopysl.egg-info/dependency_links.txt
dopysl.egg-info/requires.txt
dopysl.egg-info/top_level.txt