Metadata-Version: 1.1
Name: dopysl
Version: 0.0.2
Summary: Digital Ocean PYthon client that Sucks Less
Home-page: https://github.com/t0mk/dopysl
Author: Tomas Karasek
Author-email: tom.to.the.k@gmail.com
License: The MIT License (MIT)
